sfn/__init__.py
sfn/__main__.py
sfn/cmd/__init__.py
sfn/cmd/describe_state_machine.py
sfn/cmd/list_executions.py
sfn/cmd/list_state_machines.py
sfn/cmd/state_machine_graph.py
sfn/util/__init__.py
sfn/util/asset/__init__.py
sfn/util/asset/aws_icon.py
sfn-0.1.0.dist-info/METADATA
sfn-0.1.0.dist-info/WHEEL
sfn-0.1.0.dist-info/entry_points.txt
sfn-0.1.0.dist-info/RECORD
